InteractiveHtmlBom/.gitattributes
InteractiveHtmlBom/Run.bat
InteractiveHtmlBom/__init__.py
InteractiveHtmlBom/dialog_test.py
InteractiveHtmlBom/errors.py
InteractiveHtmlBom/generate_interactive_bom.py
InteractiveHtmlBom/icon.png
InteractiveHtmlBom/version.py
InteractiveHtmlBom/core/__init__.py
InteractiveHtmlBom/core/config.py
InteractiveHtmlBom/core/fontparser.py
InteractiveHtmlBom/core/ibom.py
InteractiveHtmlBom/core/lzstring.py
InteractiveHtmlBom/core/newstroke_font.py
InteractiveHtmlBom/core/units.py
InteractiveHtmlBom/dialog/__init__.py
InteractiveHtmlBom/dialog/dialog_base.py
InteractiveHtmlBom/dialog/settings_dialog.py
InteractiveHtmlBom/dialog/bitmaps/btn-arrow-down.png
InteractiveHtmlBom/dialog/bitmaps/btn-arrow-up.png
InteractiveHtmlBom/dialog/bitmaps/btn-minus.png
InteractiveHtmlBom/dialog/bitmaps/btn-plus.png
InteractiveHtmlBom/dialog/bitmaps/btn-question.png
InteractiveHtmlBom/ecad/__init__.py
InteractiveHtmlBom/ecad/common.py
InteractiveHtmlBom/ecad/easyeda.py
InteractiveHtmlBom/ecad/fusion_eagle.py
InteractiveHtmlBom/ecad/genericjson.py
InteractiveHtmlBom/ecad/kicad.py
InteractiveHtmlBom/ecad/svgpath.py
InteractiveHtmlBom/ecad/kicad_extra/__init__.py
InteractiveHtmlBom/ecad/kicad_extra/netlistparser.py
InteractiveHtmlBom/ecad/kicad_extra/parser_base.py
InteractiveHtmlBom/ecad/kicad_extra/sexpressions.py
InteractiveHtmlBom/ecad/kicad_extra/xmlparser.py
InteractiveHtmlBom/ecad/schema/genericjsonpcbdata_v1.schema
InteractiveHtmlBom/i18n/language_en.bat
InteractiveHtmlBom/i18n/language_zh.bat
InteractiveHtmlBom/web/ibom.css
InteractiveHtmlBom/web/ibom.html
InteractiveHtmlBom/web/ibom.js
InteractiveHtmlBom/web/lz-string.js
InteractiveHtmlBom/web/pep.js
InteractiveHtmlBom/web/render.js
InteractiveHtmlBom/web/split.js
InteractiveHtmlBom/web/table-util.js
InteractiveHtmlBom/web/util.js
interactivehtmlbom-2.10.0.dist-info/METADATA
interactivehtmlbom-2.10.0.dist-info/WHEEL
interactivehtmlbom-2.10.0.dist-info/entry_points.txt
interactivehtmlbom-2.10.0.dist-info/licenses/LICENSE
interactivehtmlbom-2.10.0.dist-info/RECORD
