Metadata-Version: 2.4
Name: InteractiveHtmlBom
Version: 2.10.0
Summary: Generate Interactive Html BOM for your electronics projects
Project-URL: Documentation, https://github.com/openscopeproject/InteractiveHtmlBom/wiki
Project-URL: Issues, https://github.com/openscopeproject/InteractiveHtmlBom/issues
Project-URL: Source, https://github.com/openscopeproject/InteractiveHtmlBom
Author-email: qu1ck <anlutsenko@gmail.com>
License-Expression: MIT
License-File: LICENSE
Keywords: Eagle,EasyEDA,KiCad,ibom
Classifier: Development Status :: 5 - Production/Stable
Classifier: License :: OSI Approved :: MIT License
Classifier: Operating System :: OS Independent
Classifier: Programming Language :: Python :: 3
Classifier: Topic :: Scientific/Engineering :: Electronic Design Automation (EDA)
Classifier: Topic :: Utilities
Requires-Python: >=3.8
Requires-Dist: jsonschema>=4.1
Requires-Dist: wxpython>=4.0
